iotlabcli/__init__.py
iotlabcli/admin.py
iotlabcli/associations.py
iotlabcli/auth.py
iotlabcli/experiment.py
iotlabcli/helpers.py
iotlabcli/node.py
iotlabcli/profile.py
iotlabcli/rest.py
iotlabcli/robot.py
iotlabcli/status.py
iotlabcli/parser/__init__.py
iotlabcli/parser/admin.py
iotlabcli/parser/auth.py
iotlabcli/parser/common.py
iotlabcli/parser/experiment.py
iotlabcli/parser/help_msgs.py
iotlabcli/parser/main.py
iotlabcli/parser/node.py
iotlabcli/parser/profile.py
iotlabcli/parser/robot.py
iotlabcli/parser/status.py
iotlabcli/parser/help/submit_list_help.md
iotlabcli/parser/help/submit_site_association_help.md
iotlabcli/tests/__init__.py
iotlabcli/tests/admin_parser_test.py
iotlabcli/tests/admin_test.py
iotlabcli/tests/associations_test.py
iotlabcli/tests/auth_parser_test.py
iotlabcli/tests/auth_test.py
iotlabcli/tests/c23.py
iotlabcli/tests/common_parser_test.py
iotlabcli/tests/experiment_parser_test.py
iotlabcli/tests/experiment_test.py
iotlabcli/tests/helpers_test.py
iotlabcli/tests/main_parser_test.py
iotlabcli/tests/my_mock.py
iotlabcli/tests/node_parser_test.py
iotlabcli/tests/node_test.py
iotlabcli/tests/profile_parser_test.py
iotlabcli/tests/profile_test.py
iotlabcli/tests/rest_test.py
iotlabcli/tests/robot_parser_test.py
iotlabcli/tests/robot_test.py
iotlabcli/tests/status_parser_test.py
iotlabcli/tests/status_test.py
iotlabcli-3.2.0.data/scripts/iotlab
iotlabcli-3.2.0.data/scripts/iotlab-auth
iotlabcli-3.2.0.data/scripts/iotlab-experiment
iotlabcli-3.2.0.data/scripts/iotlab-node
iotlabcli-3.2.0.data/scripts/iotlab-profile
iotlabcli-3.2.0.data/scripts/iotlab-robot
iotlabcli-3.2.0.data/scripts/iotlab-status
iotlabcli-3.2.0.dist-info/AUTHORS
iotlabcli-3.2.0.dist-info/COPYING
iotlabcli-3.2.0.dist-info/METADATA
iotlabcli-3.2.0.dist-info/WHEEL
iotlabcli-3.2.0.dist-info/top_level.txt
iotlabcli-3.2.0.dist-info/RECORD
