Metadata-Version: 2.1
Name: iotlabcli
Version: 3.2.0
Summary: IoT-LAB testbed command-line client
Home-page: http://www.iot-lab.info
Author: IoT-LAB Team
Author-email: admin@iot-lab.info
License: CeCILL v2.1
Download-URL: http://github.com/iot-lab/cli-tools/
Platform: UNKNOWN
Classifier: Development Status :: 5 - Production/Stable
Classifier: Programming Language :: Python
Classifier: Programming Language :: Python :: 2
Classifier: Programming Language :: Python :: 2.7
Classifier: Programming Language :: Python :: 3
Classifier: Programming Language :: Python :: 3.4
Classifier: Programming Language :: Python :: 3.5
Classifier: Programming Language :: Python :: 3.6
Classifier: Programming Language :: Python :: 3.7
Classifier: Intended Audience :: End Users/Desktop
Classifier: Environment :: Console
Classifier: Topic :: Utilities
Requires-Python: >=2.7, !=3.0.*, !=3.1.*, !=3.2.*, !=3.3.*
Requires-Dist: requests (>2.4.2)
Requires-Dist: jmespath
Provides-Extra: secure
Requires-Dist: pyOpenSSL ; extra == 'secure'
Requires-Dist: ndg-httpsclient ; extra == 'secure'
Requires-Dist: pyasn1 ; extra == 'secure'
